fresco_flash/__init__.py
fresco_flash/flash.py
fresco_flash/test_flash.py
fresco_flash-1.0.0.dist-info/DESCRIPTION.rst
fresco_flash-1.0.0.dist-info/METADATA
fresco_flash-1.0.0.dist-info/RECORD
fresco_flash-1.0.0.dist-info/WHEEL
fresco_flash-1.0.0.dist-info/metadata.json
fresco_flash-1.0.0.dist-info/top_level.txt
