Metadata-Version: 2.0
Name: fresco-flash
Version: 1.0.0
Summary: UNKNOWN
Home-page: UNKNOWN
Author: Oliver Cope
Author-email: oliver@redgecko.org
License: Apache
Platform: UNKNOWN
Requires-Dist: fresco (>=0.3.0dev)
Requires-Dist: MarkupSafe
